{
  "rules": {
    "questions": {
      "$uid": {
        "$questionId":{
          ".read":  "( auth.uid !== null && $uid === auth.uid ) ||  root.child('/users/'+auth.uid+'/supervisedBy').val().contains($uid)",
          ".write": "( auth.uid !== null && $uid === auth.uid ) &&  root.child('/users/'+auth.uid+'/userType').val() === 1"
        }
      }
    },
    "answers": {
      ".read":  true,
      ".write": true
    },
    "users":{
      "$uid": {
        ".read":    "( auth.uid !== null && $uid === auth.uid ) ||  root.child('/users/'+auth.uid+'/userType').val() === 1",
        ".write":   "( auth.uid !== null && $uid === auth.uid ) ||  root.child('/users/'+auth.uid+'/userType').val() === 1",
        "supervising": {
          ".read":  "  auth.uid !== null                        &&  root.child('/users/'+auth.uid+'/userType').val() === 1",
          ".write": "( auth.uid !== null && $uid === auth.uid ) &&  root.child('/users/'+auth.uid+'/userType').val() === 1 "
        },
        "supervisedBy": {
          ".read":  "( auth.uid !== null && $uid === auth.uid ) ||  root.child('/users/'+auth.uid+'/userType').val() === 1",
          ".write": "  auth.uid !== null                        &&  root.child('/users/'+auth.uid+'/userType').val() === 1"
        }, 
        "companyNames": {
          ".read":  "( auth.uid !== null && $uid === auth.uid ) ||  root.child('/users/'+auth.uid+'/userType').val() === 1",
          ".write": "  auth.uid !== null                        &&  root.child('/users/'+auth.uid+'/userType').val() === 1"
        }
      }
    }
  }
}